LICENSE
MANIFEST.in
README.md
README.rst
README_FILE_HIERARCHY.png
README_PIPELINE.png
setup.py
example/config_app.yaml
example/1.1/en-US/config-local.yaml
example/1.1/en-US/description.txt
example/1.1/en-US/keywords.txt
example/1.1/en-US/screenshots/ipad/1.png
example/1.1/en-US/screenshots/ipad/2.png
example/1.1/en-US/screenshots/iphone_3.5in/1.png
example/1.1/en-US/screenshots/iphone_4in/screen 1.png
example/1.1/en-US/screenshots/iphone_4in/screen 2.png
example/1.2/el-GR/config-local.yaml
example/1.2/el-GR/description.txt
example/1.2/el-GR/keywords.txt
example/1.2/en-US/config-local.yaml
example/1.2/en-US/description.txt
example/1.2/en-US/keywords.txt
example/1.2/en-US/whats_new.txt
example/1.2/en-US/screenshots/ipad/1.png
example/1.2/en-US/screenshots/ipad/2.png
example/1.2/en-US/screenshots/iphone_3.5in/1.png
example/1.2/en-US/screenshots/iphone_4.7in/screen-1.png
example/1.2/en-US/screenshots/iphone_4in/screen 1.png
example/1.2/en-US/screenshots/iphone_4in/screen 2.png
example/1.2/en-US/screenshots/iphone_5.5in/screen-1.png
itunesfs.egg-info/PKG-INFO
itunesfs.egg-info/SOURCES.txt
itunesfs.egg-info/dependency_links.txt
itunesfs.egg-info/entry_points.txt
itunesfs.egg-info/requires.txt
itunesfs.egg-info/top_level.txt
itunesfslib/__init__.py
itunesfslib/command_line.py
itunesfslib/converter.py
itunesfslib/helpers.py
itunesfslib/humanyaml.py