Metadata-Version: 1.1
Name: itunesfs
Version: 1.0.0.9
Summary: Script (python3 atm) for generating an iTunes Connect package (.itmsp) straight from your file system
Home-page: https://github.com/evilwindowdog/itunesfs
Author: Petros Douvantzis
Author-email: petrakeas@gmail.com
License: MIT
Keywords: itunesconnect,localization,yaml,apple,itunes,iTMStransporter,iOS
Platform: UNKNOWN
Classifier: Intended Audience :: Developers
Classifier: License :: OSI Approved :: MIT License
Classifier: Programming Language :: Python :: 3
Classifier: Programming Language :: Python :: 3.0
Classifier: Programming Language :: Python :: 3.1
Classifier: Programming Language :: Python :: 3.2
